HISTORY.md
MANIFEST.in
README.md
setup.py
django_sae/__init__.py
django_sae.egg-info/PKG-INFO
django_sae.egg-info/SOURCES.txt
django_sae.egg-info/dependency_links.txt
django_sae.egg-info/requires.txt
django_sae.egg-info/top_level.txt
django_sae.egg-info/zip-safe
django_sae/cache/__init__.py
django_sae/cache/backends.py
django_sae/cache/managers.py
django_sae/cache/models.py
django_sae/cache/tests/__init__.py
django_sae/cache/tests/base.py
django_sae/cache/tests/models.py
django_sae/cache/tests/test_backends.py
django_sae/cache/tests/test_managers.py
django_sae/cache/tests/test_models.py
django_sae/conf/__init__.py
django_sae/conf/settings.py
django_sae/contrib/__init__.py
django_sae/contrib/tasks/__init__.py
django_sae/contrib/tasks/cron.py
django_sae/contrib/tasks/models.py
django_sae/contrib/tasks/operations.py
django_sae/contrib/tasks/settings.py
django_sae/contrib/tasks/urls.py
django_sae/contrib/tasks/views.py
django_sae/contrib/tasks/tests/__init__.py
django_sae/contrib/tasks/tests/base.py
django_sae/contrib/tasks/tests/operations.py
django_sae/contrib/tasks/tests/test_cron.py
django_sae/contrib/tasks/tests/test_operations.py
django_sae/contrib/tasks/tests/test_views.py
django_sae/contrib/tasks/tests/views.py
django_sae/db/__init__.py
django_sae/db/models.py
django_sae/db/repository.py
django_sae/db/routers.py
django_sae/db/utils.py
django_sae/management/__init__.py
django_sae/management/commands/__init__.py
django_sae/management/commands/compress_site_packages.py
django_sae/management/commands/sae_migrate.py
django_sae/management/commands/upgrade_requirements.py
django_sae/utils/__init__.py
django_sae/utils/counts.py
django_sae/utils/decorators.py
django_sae/utils/log.py
django_sae/utils/taskqueue.py
django_sae/utils/text.py
django_sae/utils/timestamp.py