Metadata-Version: 1.1
Name: django-sae
Version: 0.2.1
Summary: for django in sae
Home-page: https://github.com/smallcode/django-sae
Author: smallcode
Author-email: 45945756@qq.com
License: Apache 2.0
Platform: UNKNOWN
Classifier: Development Status :: 5 - Production/Stable
Classifier: Environment :: Web Environment
Classifier: Framework :: Django
Classifier: Intended Audience :: Developers
Classifier: License :: OSI Approved :: Apache Software License
Classifier: Programming Language :: Python
Classifier: Topic :: Software Development :: Libraries :: Python Modules
